{"nodes": [{"id": "c_users_pc_desktop_agency_handling_components_customer_client_tsx", "label": "customer-client.tsx", "file_type": "code", "source_file": "C:\\Users\\pc\\Desktop\\agency-handling\\components\\customer-client.tsx", "source_location": "L1"}, {"id": "customer_client_submitbutton", "label": "SubmitButton()", "file_type": "code", "source_file": "C:\\Users\\pc\\Desktop\\agency-handling\\components\\customer-client.tsx", "source_location": "L19"}, {"id": "customer_client_actionwrapper", "label": "actionWrapper()", "file_type": "code", "source_file": "C:\\Users\\pc\\Desktop\\agency-handling\\components\\customer-client.tsx", "source_location": "L32"}], "edges": [{"source": "c_users_pc_desktop_agency_handling_components_customer_client_tsx", "target": "react", "relation": "imports_from", "confidence": "EXTRACTED", "source_file": "C:\\Users\\pc\\Desktop\\agency-handling\\components\\customer-client.tsx", "source_location": "L2", "weight": 1.0}, {"source": "c_users_pc_desktop_agency_handling_components_customer_client_tsx", "target": "react_dialog", "relation": "imports_from", "confidence": "EXTRACTED", "source_file": "C:\\Users\\pc\\Desktop\\agency-handling\\components\\customer-client.tsx", "source_location": "L3", "weight": 1.0}, {"source": "c_users_pc_desktop_agency_handling_components_customer_client_tsx", "target": "lucide_react", "relation": "imports_from", "confidence": "EXTRACTED", "source_file": "C:\\Users\\pc\\Desktop\\agency-handling\\components\\customer-client.tsx", "source_location": "L4", "weight": 1.0}, {"source": "c_users_pc_desktop_agency_handling_components_customer_client_tsx", "target": "customer_actions", "relation": "imports_from", "confidence": "EXTRACTED", "source_file": "C:\\Users\\pc\\Desktop\\agency-handling\\components\\customer-client.tsx", "source_location": "L5", "weight": 1.0}, {"source": "c_users_pc_desktop_agency_handling_components_customer_client_tsx", "target": "badge", "relation": "imports_from", "confidence": "EXTRACTED", "source_file": "C:\\Users\\pc\\Desktop\\agency-handling\\components\\customer-client.tsx", "source_location": "L6", "weight": 1.0}, {"source": "c_users_pc_desktop_agency_handling_components_customer_client_tsx", "target": "button", "relation": "imports_from", "confidence": "EXTRACTED", "source_file": "C:\\Users\\pc\\Desktop\\agency-handling\\components\\customer-client.tsx", "source_location": "L7", "weight": 1.0}, {"source": "c_users_pc_desktop_agency_handling_components_customer_client_tsx", "target": "input", "relation": "imports_from", "confidence": "EXTRACTED", "source_file": "C:\\Users\\pc\\Desktop\\agency-handling\\components\\customer-client.tsx", "source_location": "L8", "weight": 1.0}, {"source": "c_users_pc_desktop_agency_handling_components_customer_client_tsx", "target": "textarea", "relation": "imports_from", "confidence": "EXTRACTED", "source_file": "C:\\Users\\pc\\Desktop\\agency-handling\\components\\customer-client.tsx", "source_location": "L9", "weight": 1.0}, {"source": "c_users_pc_desktop_agency_handling_components_customer_client_tsx", "target": "utils", "relation": "imports_from", "confidence": "EXTRACTED", "source_file": "C:\\Users\\pc\\Desktop\\agency-handling\\components\\customer-client.tsx", "source_location": "L10", "weight": 1.0}, {"source": "c_users_pc_desktop_agency_handling_components_customer_client_tsx", "target": "utils", "relation": "imports_from", "confidence": "EXTRACTED", "source_file": "C:\\Users\\pc\\Desktop\\agency-handling\\components\\customer-client.tsx", "source_location": "L11", "weight": 1.0}, {"source": "c_users_pc_desktop_agency_handling_components_customer_client_tsx", "target": "customer_client_submitbutton", "relation": "contains", "confidence": "EXTRACTED", "source_file": "C:\\Users\\pc\\Desktop\\agency-handling\\components\\customer-client.tsx", "source_location": "L19", "weight": 1.0}, {"source": "c_users_pc_desktop_agency_handling_components_customer_client_tsx", "target": "customer_client_actionwrapper", "relation": "contains", "confidence": "EXTRACTED", "source_file": "C:\\Users\\pc\\Desktop\\agency-handling\\components\\customer-client.tsx", "source_location": "L32", "weight": 1.0}], "raw_calls": [{"caller_nid": "customer_client_actionwrapper", "callee": "action", "source_file": "C:\\Users\\pc\\Desktop\\agency-handling\\components\\customer-client.tsx", "source_location": "L33"}, {"caller_nid": "customer_client_actionwrapper", "callee": "setMessage", "source_file": "C:\\Users\\pc\\Desktop\\agency-handling\\components\\customer-client.tsx", "source_location": "L34"}, {"caller_nid": "customer_client_actionwrapper", "callee": "setTimeout", "source_file": "C:\\Users\\pc\\Desktop\\agency-handling\\components\\customer-client.tsx", "source_location": "L36"}]}